LICENSE
MANIFEST.in
README.rst
horovod.exp
horovod.lds
setup.py
.github/ISSUE_TEMPLATE/bug_report.md
.github/ISSUE_TEMPLATE/feature_request.md
.github/ISSUE_TEMPLATE/question.md
bin/horovodrun
docs/mlsl.md
horovod/__init__.py
horovod/_keras/__init__.py
horovod/_keras/callbacks.py
horovod/common/__init__.py
horovod/common/basics.py
horovod/common/common.cc
horovod/common/common.h
horovod/common/controller.cc
horovod/common/controller.h
horovod/common/fusion_buffer_manager.cc
horovod/common/fusion_buffer_manager.h
horovod/common/global_state.h
horovod/common/half.cc
horovod/common/half.h
horovod/common/hashes.h
horovod/common/logging.cc
horovod/common/logging.h
horovod/common/message.cc
horovod/common/message.h
horovod/common/operations.cc
horovod/common/operations.h
horovod/common/parameter_manager.cc
horovod/common/parameter_manager.h
horovod/common/response_cache.cc
horovod/common/response_cache.h
horovod/common/stall_inspector.cc
horovod/common/stall_inspector.h
horovod/common/tensor_queue.cc
horovod/common/tensor_queue.h
horovod/common/timeline.cc
horovod/common/timeline.h
horovod/common/util.py
horovod/common/gloo/gloo_context.cc
horovod/common/gloo/gloo_context.h
horovod/common/gloo/gloo_controller.cc
horovod/common/gloo/gloo_controller.h
horovod/common/gloo/gloo_store.h
horovod/common/gloo/http_store.cc
horovod/common/gloo/http_store.h
horovod/common/gloo/memory_store.cc
horovod/common/gloo/memory_store.h
horovod/common/mpi/ddl_mpi_context_manager.cc
horovod/common/mpi/ddl_mpi_context_manager.h
horovod/common/mpi/mpi_context.cc
horovod/common/mpi/mpi_context.h
horovod/common/mpi/mpi_controller.cc
horovod/common/mpi/mpi_controller.h
horovod/common/ops/adasum_cuda_operations.cc
horovod/common/ops/adasum_cuda_operations.h
horovod/common/ops/adasum_mpi_operations.cc
horovod/common/ops/adasum_mpi_operations.h
horovod/common/ops/collective_operations.cc
horovod/common/ops/collective_operations.h
horovod/common/ops/cuda_operations.cc
horovod_adasum.egg-info/PKG-INFO
horovod_adasum.egg-info/SOURCES.txt
horovod_adasum.egg-info/dependency_links.txt
horovod_adasum.egg-info/not-zip-safe
horovod_adasum.egg-info/requires.txt
horovod_adasum.egg-info/top_level.txt
