Metadata-Version: 1.1
Name: horovod-adasum
Version: 0.18.2a0
Summary: Horovod with Adasum for highly scalable distributed training.
Home-page: https://www.microsoft.com/en-us/research/project/parasail/
Author: The Horovod Authors
Author-email: UNKNOWN
License: UNKNOWN
Platform: UNKNOWN
Classifier: License :: OSI Approved :: Apache Software License
